{
    "cartes": [
        {
            "Nom" : "Archers",
            "img" : "../images_cartes/archers.png",
            "Type" : "Troupe terrestre",
            "Rareté" : "Commune",
            "Elixir" : "3",
            "Points de vie": "304",
            "Dégâts" : "107",
            "Effet de zone" : "Non",
            "Portée" : "5",
            "Vitesse de frappe" : "0.9s",
            "Vitesse" : "Moyen",
            "Cible" : "Sol & Air",
            "Nombre" : "2"
        },
        {
            "Nom" : "Artificière",
            "img" : "../images_cartes/artificiere.png",
            "Type" : "Troupe terrestre",
            "Rareté" : "Commune",
            "Elixir" : "3",
            "Points de vie": "304",
            "Dégâts" : "320",
            "Effet de zone" : "Oui",
            "Portée" : "6",
            "Vitesse de frappe" : "3s",
            "Vitesse" : "Rapide",
            "Cible" : "Sol & Air",
            "Nombre" : "1"
        },
        {
            "Nom" : "Barbares",
            "img" : "../images_cartes/barbares.png",
            "Type" : "Troupe terrestre",
            "Rareté" : "Commune",
            "Elixir" : "5",
            "Points de vie": "670",
            "Dégâts" : "192",
            "Effet de zone" : "Non",
            "Portée" : "0.7",
            "Vitesse de frappe" : "1.3s",
            "Vitesse" : "Moyen",
            "Cible" : "Sol",
            "Nombre" : "5"
        },
        {
            "Nom" : "Barbares d'Elites",
            "img" : "../images_cartes/barbares_delites.png",
            "Type" : "Troupe terrestre",
            "Rareté" : "Commune",
            "Elixir" : "6",
            "Points de vie": "1341",
            "Dégâts" : "384",
            "Effet de zone" : "Non",
            "Portée" : "1.2",
            "Vitesse de frappe" : "1.4s",
            "Vitesse" : "Rapide",
            "Cible" : "Sol",
            "Nombre" : "2"
        },
        {
            "Nom" : "Berserker",
            "img" : "../images_cartes/berserker.png",
            "Type" : "Troupe terrestre",
            "Rareté" : "Commune",
            "Elixir" : "2",
            "Points de vie": "832",
            "Dégâts" : "102",
            "Effet de zone" : "Non",
            "Portée" : "0.8",
            "Vitesse de frappe" : "0.6s",
            "Vitesse" : "Rapide",
            "Cible" : "Sol",
            "Nombre" : "1"
        },
        {
            "Nom" : "Bombardier",
            "img" : "../images_cartes/bombardier.png",
            "Type" : "Troupe terrestre",
            "Rareté" : "Commune",
            "Elixir" : "2",
            "Points de vie": "332",
            "Dégâts" : "225",
            "Effet de zone" : "Oui",
            "Portée" : "4.5",
            "Vitesse de frappe" : "1.8s",
            "Vitesse" : "Moyen",
            "Cible" : "Sol",
            "Nombre" : "1"
        },
        {
            "Nom" : "Boule de Neige",
            "img" : "../images_cartes/boule_de_neige.png",
            "Type" : "Sort",
            "Rareté" : "Commune",
            "Elixir" : "2",
            "Dégâts" : "179",
            "Dégâts Couronnés": "54",
            "Effet de zone" : "Oui",
            "Rayon" : "2.5",
            "Cible" : "Toutes"
        },
        {
            "Nom" : "Canon",
            "img" : "../images_cartes/canon.png",
            "Type" : "Bâtiment",
            "Rareté" : "Commune",
            "Elixir" : "3",
            "Points de vie": "824",
            "Dégâts" : "212",
            "Effet de zone" : "Non",
            "Portée" : "5.5",
            "Vitesse de frappe" : "0.9s",
            "Cible" : "Sol"
        },
        {
            "Nom" : "Chauves-Souris",
            "img" : "../images_cartes/chauves-souris.png",
            "Type" : "Troupe aérienne",
            "Rareté" : "Commune",
            "Elixir" : "2",
            "Points de vie": "81",
            "Dégâts" : "81",
            "Effet de zone" : "Non",
            "Portée" : "1.2",
            "Vitesse de frappe" : "1.3s",
            "Vitesse" : "Très rapide",
            "Cible" : "Sol & Air",
            "Nombre" : "5"
        },
        {
            "Nom" : "Chevalier",
            "img" : "../images_cartes/chevalier.png",
            "Type" : "Troupe terrestre",
            "Rareté" : "Commune",
            "Elixir" : "3",
            "Points de vie": "1766",
            "Dégâts" : "202",
            "Effet de zone" : "Non",
            "Portée" : "1.2",
            "Vitesse de frappe" : "1.2s",
            "Vitesse" : "Moyen",
            "Cible" : "Sol",
            "Nombre" : "1"
        },
        {
            "Nom" : "Colis Royal",
            "img" : "../images_cartes/colis_royal.png",
            "Type" : "Sort",
            "Rareté" : "Commune",
            "Elixir" : "3",
            "Dégâts" : "437",
            "Dégâts Couronnés": "Aucun",
            "Effet de zone" : "Oui",
            "Rayon" : "3",
            "Cible" : "Toutes"
        },
        {
            "Nom" : "Dragons Squelettes",
            "img" : "../images_cartes/dragons_squelettes.png",
            "Type" : "Troupe aérienne",
            "Rareté" : "Commune",
            "Elixir" : "4",
            "Points de vie": "560",
            "Dégâts" : "161",
            "Effet de zone" : "Oui",
            "Portée" : "3.5",
            "Vitesse de frappe" : "1.9s",
            "Vitesse" : "Rapide",
            "Cible" : "Sol & Air",
            "Nombre" : "2"
        },
        {
            "Nom" : "Electrocution",
            "img" : "../images_cartes/electrocution.png",
            "Type" : "Sort",
            "Rareté" : "Commune",
            "Elixir" : "2",
            "Dégâts" : "192",
            "Dégâts Couronnés": "58",
            "Effet de zone" : "Oui",
            "Portée" : "2.5",
            "Rayon" : "2.5",
            "Cible" : "Toutes"
        },
        {
            "Nom" : "Electro-Esprit",
            "img" : "../images_cartes/electro-esprit.png",
            "Type" : "Troupe terrestre",
            "Rareté" : "Commune",
            "Elixir" : "1",
            "Points de vie": "230",
            "Dégâts" : "99",
            "Effet de zone" : "Oui (en chaîne)",
            "Portée" : "2.5",
            "Vitesse" : "Très rapide",
            "Cible" : "Sol & Air",
            "Nombre" : "1"
        },
        {
            "Nom" : "Esprit de Feu",
            "img" : "../images_cartes/esprit_de_feu.png",
            "Type" : "Troupe terrestre",
            "Rareté" : "Commune",
            "Elixir" : "1",
            "Points de vie": "230",
            "Dégâts" : "207",
            "Effet de zone" : "Oui",
            "Portée" : "2.5",
            "Vitesse" : "Très rapide",
            "Cible" : "Sol & Air",
            "Nombre" : "1"
        },
        {
            "Nom" : "Esprit de Glace",
            "img" : "../images_cartes/esprit_de_glace.png",
            "Type" : "Troupe terrestre",
            "Rareté" : "Commune",
            "Elixir" : "1",
            "Points de vie": "230",
            "Dégâts" : "110",
            "Effet de zone" : "Oui",
            "Portée" : "2.5",
            "Vitesse" : "Très rapide",
            "Cible" : "Sol & Air",
            "Nombre" : "1"
        },
        {
            "Nom" : "Flèches",
            "img" : "../images_cartes/fleches.png",
            "Type" : "Sort",
            "Rareté" : "Commune",
            "Elixir" : "3",
            "Dégâts" : "366",
            "Dégâts Couronnés": "93",
            "Effet de zone" : "Oui",
            "Rayon" : "4",
            "Cible" : "Toutes"
        },
        {
            "Nom" : "Fripons",
            "img" : "../images_cartes/fripons.png",
            "Type" : "Troupe terrestre",
            "Rareté" : "Commune",
            "Elixir" : "5",
            "Points de vie": "1940 / 261",
            "Dégâts" : "133",
            "Effet de zone" : "Non",
            "Portée" : "Corps à corps & distance",
            "Vitesse de frappe" : "1.5s / 1s",
            "Vitesse" : "Moyen",
            "Cible" : "Sol & Air",
            "Nombre" : "3"
        },
        {
            "Nom" : "Fût à Squelettes",
            "img" : "../images_cartes/fut_a_squelettes.png",
            "Type" : "Troupe aérienne",
            "Rareté" : "Commune",
            "Elixir" : "4",
            "Points de vie du fût": "532",
            "Dégâts mortels" : "145",
            "Effet de zone" : "Oui",
            "Portée" : "0.5",
            "Vitesse" : "Rapide",
            "Cible" : "Bâtiment & Tour",
            "Nombre de squelettes" : "7",
            "Autres" : "+ stats squelettes"
        },
        {
            "Nom" : "Gang de Goblins",
            "img" : "../images_cartes/gang_de_goblins.png",
            "Type" : "Troupe terrestre",
            "Rareté" : "Commune",
            "Elixir" : "3",
            "Points de vie": "202 & 133",
            "Dégâts" : "120 & 81",
            "Effet de zone" : "Non",
            "Portée" : "0.5 & 5.5",
            "Vitesse de frappe" : "1.1s & 1.7s",
            "Vitesse" : "Très rapide",
            "Cible" : "Sol & Air",
            "Nombre de goblins" : "3 & 3",
            "Autres" : "+ stats goblins & gob à lances"
        },
        {
            "Nom" : "Gargouilles",
            "img" : "../images_cartes/gargouilles.png",
            "Type" : "Troupe aérienne",
            "Rareté" : "Commune",
            "Elixir" : "3",
            "Points de vie": "230",
            "Dégâts" : "117",
            "Effet de zone" : "Non",
            "Portée" : "2",
            "Vitesse de frappe" : "1s",
            "Vitesse" : "Rapide",
            "Cible" : "Sol & Air",
            "Nombre" : "3"
        },
        {
            "Nom" : "Géant Royal",
            "img" : "../images_cartes/geant_royal.png",
            "Type" : "Troupe terrestre",
            "Rareté" : "Commune",
            "Elixir" : "6",
            "Points de vie": "3164",
            "Dégâts" : "307",
            "Effet de zone" : "Oui",
            "Portée" : "5",
            "Vitesse de frappe" : "1.7s",
            "Vitesse" : "Lent",
            "Cible" : "Bâtiment & Tour",
            "Nombre" : "1"
        },
        {
            "Nom" : "Goblins",
            "img" : "../images_cartes/goblins.png",
            "Type" : "Troupe terrestre",
            "Rareté" : "Commune",
            "Elixir" : "2",
            "Points de vie" : "202",
            "Dégâts" : "120",
            "Effet de zone" : "Non",
            "Portée" : "0.5",
            "Vitesse de frappe" : "1.1s",
            "Vitesse" : "Très rapide",
            "Cible" : "Sol",
            "Nombre" : "4"
        },
        {
            "Nom" : "Goblins à Lances",
            "img" : "../images_cartes/goblins_a_lances.png",
            "Type" : "Troupe terrestre",
            "Rareté" : "Commune",
            "Elixir" : "2",
            "Points de vie" : "133",
            "Dégâts" : "81",
            "Effet de zone" : "Non",
            "Portée" : "5.5",
            "Vitesse de frappe" : "1.7s",
            "Vitesse" : "Très rapide",
            "Cible" : "Sol & Air",
            "Nombre" : "3"
        },
        {
            "Nom" : "Horde de Gargouilles",
            "img" : "../images_cartes/horde_de_gargouilles.png",
            "Type" : "Troupe aérienne",
            "Rareté" : "Commune",
            "Elixir" : "5",
            "Points de vie": "230",
            "Dégâts" : "117",
            "Effet de zone" : "Non",
            "Portée" : "2",
            "Vitesse de frappe" : "1s",
            "Vitesse" : "Rapide",
            "Cible" : "Sol & Air",
            "Nombre" : "6"
        },
        {
            "Nom" : "Mortier",
            "img" : "../images_cartes/mortier.png",
            "Type" : "Bâtiment",
            "Rareté" : "Commune",
            "Elixir" : "4",
            "Points de vie": "1369",
            "Dégâts" : "266",
            "Effet de zone" : "Oui",
            "Portée" : "11.5",
            "Vitesse de frappe" : "5s",
            "Cible" : "Sol"
        },  
        {
            "Nom" : "Recrues Royales",
            "img" : "../images_cartes/recrues_royales.png",
            "Type" : "Troupe terrestre",
            "Rareté" : "Commune",
            "Elixir" : "7",
            "Points de vie": "547",
            "Bouclier" : "240",
            "Dégâts" : "133",
            "Effet de zone" : "Non",
            "Portée" : "1.6",
            "Vitesse de frappe" : "1.3s",
            "Vitesse" : "Moyen",
            "Cible" : "Sol",
            "Nombre" : "6"
        },
        {
            "Nom" : "Squelettes",
            "img" : "../images_cartes/squelettes.png",
            "Type" : "Troupe terrestre",
            "Rareté" : "Commune",
            "Elixir" : "1",
            "Points de vie": "81",
            "Dégâts" : "81",
            "Effet de zone" : "Non",
            "Portée" : "0.5",
            "Vitesse de frappe" : "1s",
            "Vitesse" : "Rapide",
            "Cible" : "Sol",
            "Nombre" : "3"
        },
        {
            "Nom" : "Tesla",
            "img" : "../images_cartes/tesla.png",
            "Type" : "Bâtiment",
            "Rareté" : "Commune",
            "Elixir" : "3",
            "Points de vie": "1152",
            "Dégâts" : "220",
            "Effet de zone" : "Non",
            "Portée" : "5.5",
            "Vitesse de frappe" : "1.1s",
            "Cible" : "Sol & Air"
        }

    ]


}
